supersetapiclient/__init__.py
supersetapiclient/base.py
supersetapiclient/charts.py
supersetapiclient/client.py
supersetapiclient/dashboards.py
supersetapiclient/databases.py
supersetapiclient/datasets.py
supersetapiclient/exceptions.py
supersetapiclient/saved_queries.py
superset_api_client-0.6.0.dist-info/LICENSE
superset_api_client-0.6.0.dist-info/METADATA
superset_api_client-0.6.0.dist-info/WHEEL
superset_api_client-0.6.0.dist-info/top_level.txt
superset_api_client-0.6.0.dist-info/RECORD
