Metadata-Version: 2.1
Name: superset-api-client
Version: 0.6.0
Summary: A simple REST API Client for Apache-Superset
Home-page: https://github.com/opus-42/superset-api-client
Author: Emmanuel B.
Author-email: emmanuel.bavoux@gmail.com
Classifier: Development Status :: 3 - Alpha
Requires-Python: >=3.6
License-File: LICENSE
Requires-Dist: requests (>=2.0.0)
Requires-Dist: requests-oauthlib
Requires-Dist: pyyaml (>=6.0)
Requires-Dist: cached-property ; python_version < "3.8"
Provides-Extra: build
Requires-Dist: build ; extra == 'build'
Provides-Extra: dev
Requires-Dist: flake8 ; extra == 'dev'
Requires-Dist: black ; extra == 'dev'
Requires-Dist: isort ; extra == 'dev'
Requires-Dist: pytest ; extra == 'dev'
Requires-Dist: requests-mock ; extra == 'dev'
Requires-Dist: pytest-docker ; extra == 'dev'
Requires-Dist: pytest-cov ; extra == 'dev'
Requires-Dist: coveralls ; extra == 'dev'
Requires-Dist: pre-commit ; extra == 'dev'
